swift_apple/GuessGame.py
swift_apple/GuessGameEasy.py
swift_apple/GuessGameSecondary.py
swift_apple/MITLicense.py
swift_apple/PHYSICAL_CONDITION_APPLET.py
swift_apple/Python3学习示例.py
swift_apple/__init__.py
swift_apple/animal_guess.py
swift_apple/caterpillar.py
swift_apple/caterpillar2.py
swift_apple/copyright.py
swift_apple/egg_catcher.py
swift_apple/egg_catcher_perfect.py
swift_apple/matchmaker.py
swift_apple/random.py
swift_apple/rectangle.py
swift_apple/robot_builder.py
swift_apple/screen_pet.py
swift_apple/swift.py
swift_apple/加密消息.py
swift_apple/单词九连猜.py
swift_apple/圆通万花筒.py
swift_apple/快照抓拍.py
swift_apple/星光夜空.py
swift_apple/螺旋万花筒.py
swift_module_copiseded-0.6.6.dist-info/LICENSE.txt
swift_module_copiseded-0.6.6.dist-info/METADATA
swift_module_copiseded-0.6.6.dist-info/WHEEL
swift_module_copiseded-0.6.6.dist-info/top_level.txt
swift_module_copiseded-0.6.6.dist-info/RECORD
