Metadata-Version: 2.1
Name: swift-module-copiseded
Version: 0.6.6
Summary: 本次更新并没有改变上次的库，而是将地址修改，本次更新将淘汰之前的旧版github库，将会开启一个新的库，你可以在这儿获取主要文件夹，本次更新将会在下载文件上做改变。
Home-page: https://github.com/monkeyhammercopiseded/swift-module-copiseded-new-/
Author: Monkey Hammer Copiseded
Author-email: Wf6350177@163.com
Project-URL: Bug Tracker, https://github.com/monkeyhammercopiseded/swift-module-copiseded-new-/issues
Classifier: Programming Language :: Python :: 3
Classifier: License :: OSI Approved :: MIT License
Classifier: Operating System :: OS Independent
Requires-Python: >=3.6
License-File: LICENSE.txt
